MANIFEST.in
Makefile
README.rst
requirements-docs.txt
requirements-server.txt
requirements-test.txt
requirements.txt
setup.cfg
setup.py
bin/womack
womack/__init__.py
womack/config.py
womack/namespace.py
womack/publish.py
womack/server.py
womack.egg-info/PKG-INFO
womack.egg-info/SOURCES.txt
womack.egg-info/dependency_links.txt
womack.egg-info/entry_points.txt
womack.egg-info/requires.txt
womack.egg-info/top_level.txt
womack/static/channel_test.html
womack/static/socket.io.js
womack/static/test.html
womack/static/womack.js
womack/tests/__init__.py
womack/tests/test_namespace.py
womack/tests/test_publish.py
womack/tests/test_server.py