Metadata-Version: 1.0
Name: womack
Version: 0.1
Summary: ['Womack pushes real-time javascript events from your application to clients']
Home-page: https://github.com/leapfrogdevelopment/womack
Author: Leapfrog Online
Author-email: oss@leapfrogdevelopment.com
License: UNKNOWN
Keywords: gevent,socketio,http,redis
Platform: UNKNOWN
Classifier: Development Status :: 3 - Alpha
Classifier: Intended Audience :: Developers
Classifier: License :: OSI Approved :: BSD License
Classifier: Programming Language :: Python
Classifier: Programming Language :: Python :: 2.6
Classifier: Programming Language :: Python :: 2.7
Classifier: Operating System :: OS Independent
Classifier: Natural Language :: English
Classifier: Topic :: Internet :: WWW/HTTP :: HTTP Servers
